azureml/__init__.py
azureml/rai/__init__.py
azureml/rai/utils/__init__.py
azureml/rai/utils/_version.py
azureml/rai/utils/constants.py
azureml/rai/utils/dataset_manager.py
azureml/rai/utils/mlflow_model_wrapper.py
azureml/rai/utils/model_serializer.py
azureml/rai/utils/pyfunc_model.py
azureml/rai/utils/llm_eval_benchmark/__init__.py
azureml/rai/utils/llm_eval_benchmark/e2e.py
azureml/rai/utils/llm_eval_benchmark/benchmarkutils/__init__.py
azureml/rai/utils/llm_eval_benchmark/benchmarkutils/azure_connector.py
azureml/rai/utils/llm_eval_benchmark/benchmarkutils/constants.py
azureml/rai/utils/llm_eval_benchmark/benchmarkutils/http_client.py
azureml/rai/utils/llm_eval_benchmark/benchmarkutils/tokenizer.py
azureml/rai/utils/llm_eval_benchmark/common/__init__.py
azureml/rai/utils/llm_eval_benchmark/common/data_preparer.py
azureml/rai/utils/llm_eval_benchmark/common/experiment_runner.py
azureml/rai/utils/llm_eval_benchmark/common/metrics_generator.py
azureml/rai/utils/llm_eval_benchmark/common/prompt_formatter.py
azureml/rai/utils/llm_eval_benchmark/common/request_manager.py
azureml/rai/utils/llm_eval_benchmark/common/response_parser.py
azureml/rai/utils/llm_eval_benchmark/common/scoring_manager.py
azureml/rai/utils/llm_eval_benchmark/common/model/__init__.py
azureml/rai/utils/llm_eval_benchmark/common/model/input_sample.py
azureml/rai/utils/llm_eval_benchmark/common/model/job.py
azureml/rai/utils/llm_eval_benchmark/common/model/prompt_data.py
azureml/rai/utils/llm_eval_benchmark/configs/__init__.py
azureml/rai/utils/llm_eval_benchmark/configs/aml_workspace_config.json
azureml/rai/utils/llm_eval_benchmark/configs/request_config.json
azureml/rai/utils/llm_eval_benchmark/groundedness/__init__.py
azureml/rai/utils/llm_eval_benchmark/groundedness/groundedness_benchmark_runner.py
azureml/rai/utils/telemetry/__init__.py
azureml/rai/utils/telemetry/loggerfactory.py
azureml_rai_utils-0.0.6.dist-info/DESCRIPTION.rst
azureml_rai_utils-0.0.6.dist-info/METADATA
azureml_rai_utils-0.0.6.dist-info/RECORD
azureml_rai_utils-0.0.6.dist-info/WHEEL
azureml_rai_utils-0.0.6.dist-info/entry_points.txt
azureml_rai_utils-0.0.6.dist-info/metadata.json
azureml_rai_utils-0.0.6.dist-info/top_level.txt
