Metadata-Version: 2.0
Name: azureml-rai-utils
Version: 0.0.6
Summary: Azure Machine Learning Responsible AI Utils SDK
Home-page: https://github.com/Azure/azureml-examples/tree/main/cli/responsible-ai
Author: Microsoft Corporation
License: MIT License
Keywords: AzureMachineLearning
Classifier: Development Status :: 3 - Alpha
Classifier: Intended Audience :: Developers
Classifier: Natural Language :: English
Classifier: Operating System :: OS Independent
Classifier: Programming Language :: Python
Classifier: Programming Language :: Python :: 3.8
Classifier: Programming Language :: Python :: 3.9
Classifier: Programming Language :: Python :: 3.10
Classifier: Programming Language :: Python :: 3.11
Classifier: License :: OSI Approved :: MIT License
Requires-Python: <4.0,>=3.8
Requires-Dist: azure-ai-ml
Requires-Dist: azure-identity
Requires-Dist: mlflow
Requires-Dist: azureml-mlflow
Requires-Dist: mltable
Requires-Dist: raiutils
Provides-Extra: benchmark
Requires-Dist: click; extra == "benchmark"
Requires-Dist: jinja2; extra == "benchmark"
Requires-Dist: json5; extra == "benchmark"
Requires-Dist: azure-keyvault; extra == "benchmark"
Requires-Dist: scikit-learn; extra == "benchmark"
Requires-Dist: pandas; extra == "benchmark"
Requires-Dist: numpy; extra == "benchmark"
Requires-Dist: tiktoken; extra == "benchmark"
Requires-Dist: azure-ai-ml
Requires-Dist: azure-identity
Requires-Dist: mlflow
Requires-Dist: azureml-mlflow
Requires-Dist: mltable
Requires-Dist: raiutils
Provides-Extra: benchmark
Requires-Dist: click; extra == 'benchmark'
Requires-Dist: jinja2; extra == 'benchmark'
Requires-Dist: json5; extra == 'benchmark'
Requires-Dist: azure-keyvault; extra == 'benchmark'
Requires-Dist: scikit-learn; extra == 'benchmark'
Requires-Dist: pandas; extra == 'benchmark'
Requires-Dist: numpy; extra == 'benchmark'
Requires-Dist: tiktoken; extra == 'benchmark'
